{
    "cw": {
        "\u0000": 250,
        "\u0001": 250,
        "\u0002": 250,
        "\u0003": 250,
        "\u0004": 250,
        "\u0005": 250,
        "\u0006": 250,
        "\u0007": 250,
        "\b": 250,
        "\t": 250,
        "\n": 250,
        "\u000b": 250,
        "\f": 250,
        "\r": 250,
        "\u000e": 250,
        "\u000f": 250,
        "\u0010": 250,
        "\u0011": 250,
        "\u0012": 250,
        "\u0013": 250,
        "\u0014": 250,
        "\u0015": 250,
        "\u0016": 250,
        "\u0017": 250,
        "\u0018": 250,
        "\u0019": 250,
        "\u001a": 250,
        "\u001b": 250,
        "\u001c": 250,
        "\u001d": 250,
        "\u001e": 250,
        "\u001f": 250,
        " ": 250,
        "!": 378,
        "\"": 555,
        "#": 767,
        "$": 713,
        "%": 883,
        "&": 773,
        "'": 278,
        "(": 333,
        ")": 333,
        "*": 504,
        "+": 767,
        ",": 307,
        "-": 222,
        ".": 307,
        "\/": 759,
        "0": 713,
        "1": 713,
        "2": 713,
        "3": 713,
        "4": 713,
        "5": 713,
        "6": 713,
        "7": 713,
        "8": 713,
        "9": 713,
        ":": 307,
        ";": 307,
        "<": 500,
        "=": 767,
        ">": 500,
        "?": 488,
        "@": 821,
        "A": 813,
        "B": 806,
        "C": 839,
        "D": 838,
        "E": 760,
        "F": 728,
        "G": 858,
        "H": 858,
        "I": 328,
        "J": 604,
        "K": 802,
        "L": 708,
        "M": 966,
        "N": 872,
        "O": 855,
        "P": 765,
        "Q": 855,
        "R": 809,
        "S": 720,
        "T": 674,
        "U": 816,
        "V": 770,
        "W": 1128,
        "X": 752,
        "Y": 713,
        "Z": 714,
        "[": 333,
        "\\": 759,
        "]": 333,
        "^": 500,
        "_": 500,
        "`": 500,
        "a": 694,
        "b": 677,
        "c": 697,
        "d": 704,
        "e": 642,
        "f": 609,
        "g": 720,
        "h": 726,
        "i": 290,
        "j": 505,
        "k": 685,
        "l": 574,
        "m": 819,
        "n": 744,
        "o": 713,
        "p": 652,
        "q": 723,
        "r": 687,
        "s": 616,
        "t": 569,
        "u": 690,
        "v": 650,
        "w": 959,
        "x": 635,
        "y": 599,
        "z": 609,
        "{": 333,
        "|": 500,
        "}": 333,
        "~": 667,
        "": 250,
        "\u0080": 713,
        "\u0081": 250,
        "\u0082": 307,
        "\u0083": 713,
        "\u0084": 540,
        "\u0085": 920,
        "\u0086": 539,
        "\u0087": 539,
        "\u0088": 500,
        "\u0089": 1291,
        "\u008a": 720,
        "\u008b": 313,
        "\u008c": 1189,
        "\u008d": 250,
        "\u008e": 250,
        "\u008f": 250,
        "\u0090": 250,
        "\u0091": 307,
        "\u0092": 307,
        "\u0093": 540,
        "\u0094": 540,
        "\u0095": 667,
        "\u0096": 770,
        "\u0097": 665,
        "\u0098": 500,
        "\u0099": 1017,
        "\u009a": 616,
        "\u009b": 313,
        "\u009c": 980,
        "\u009d": 250,
        "\u009e": 250,
        "\u009f": 713,
        "\u00a0": 250,
        "\u00a1": 378,
        "\u00a2": 713,
        "\u00a3": 713,
        "\u00a4": 767,
        "\u00a5": 713,
        "\u00a6": 500,
        "\u00a7": 671,
        "\u00a8": 500,
        "\u00a9": 883,
        "\u00aa": 511,
        "\u00ab": 487,
        "\u00ac": 500,
        "\u00ad": 222,
        "\u00ae": 888,
        "\u00af": 500,
        "\u00b0": 461,
        "\u00b1": 767,
        "\u00b2": 473,
        "\u00b3": 473,
        "\u00b4": 500,
        "\u00b5": 480,
        "\u00b6": 638,
        "\u00b7": 307,
        "\u00b8": 500,
        "\u00b9": 473,
        "\u00ba": 511,
        "\u00bb": 487,
        "\u00bc": 1233,
        "\u00bd": 1234,
        "\u00be": 1233,
        "\u00bf": 488,
        "\u00c0": 813,
        "\u00c1": 813,
        "\u00c2": 813,
        "\u00c3": 813,
        "\u00c4": 813,
        "\u00c5": 813,
        "\u00c6": 1163,
        "\u00c7": 839,
        "\u00c8": 760,
        "\u00c9": 760,
        "\u00ca": 760,
        "\u00cb": 760,
        "\u00cc": 328,
        "\u00cd": 328,
        "\u00ce": 328,
        "\u00cf": 328,
        "\u00d0": 838,
        "\u00d1": 872,
        "\u00d2": 855,
        "\u00d3": 855,
        "\u00d4": 855,
        "\u00d5": 855,
        "\u00d6": 855,
        "\u00d7": 767,
        "\u00d8": 855,
        "\u00d9": 816,
        "\u00da": 816,
        "\u00db": 816,
        "\u00dc": 816,
        "\u00dd": 713,
        "\u00de": 715,
        "\u00df": 1231,
        "\u00e0": 694,
        "\u00e1": 694,
        "\u00e2": 694,
        "\u00e3": 694,
        "\u00e4": 694,
        "\u00e5": 694,
        "\u00e6": 1021,
        "\u00e7": 697,
        "\u00e8": 642,
        "\u00e9": 642,
        "\u00ea": 642,
        "\u00eb": 642,
        "\u00ec": 290,
        "\u00ed": 290,
        "\u00ee": 289,
        "\u00ef": 290,
        "\u00f0": 714,
        "\u00f1": 744,
        "\u00f2": 713,
        "\u00f3": 713,
        "\u00f4": 713,
        "\u00f5": 713,
        "\u00f6": 713,
        "\u00f7": 767,
        "\u00f8": 713,
        "\u00f9": 690,
        "\u00fa": 690,
        "\u00fb": 690,
        "\u00fc": 690,
        "\u00fd": 599,
        "\u00fe": 605,
        "\u00ff": 599
    },
    "value": 599,
    "index": "\u00ff",
    "type": "TrueType",
    "name": "CopperplateBold",
    "desc": {
        "Ascent": 885,
        "Descent": -227,
        "CapHeight": 667,
        "Flags": 32,
        "FontBBox": "[-133 -250 1257 885]",
        "ItalicAngle": 0,
        "StemV": 70,
        "MissingWidth": 250
    },
    "up": -101,
    "ut": 85,
    "enc": "cp1252",
    "diff": "",
    "file": "copperplatebold.z",
    "originalsize": 61552
}